channels/__init__.py
channels/apps.py
channels/auth.py
channels/consumer.py
channels/db.py
channels/exceptions.py
channels/hacks.py
channels/http.py
channels/layers.py
channels/middleware.py
channels/routing.py
channels/sessions.py
channels/signals.py
channels/staticfiles.py
channels/utils.py
channels/worker.py
channels/generic/__init__.py
channels/generic/http.py
channels/generic/websocket.py
channels/management/__init__.py
channels/management/commands/__init__.py
channels/management/commands/runserver.py
channels/management/commands/runworker.py
channels/security/__init__.py
channels/security/websocket.py
channels/testing/__init__.py
channels/testing/http.py
channels/testing/live.py
channels/testing/websocket.py
bulb_channels-2.4.0.1.dist-info/LICENSE
bulb_channels-2.4.0.1.dist-info/METADATA
bulb_channels-2.4.0.1.dist-info/WHEEL
bulb_channels-2.4.0.1.dist-info/top_level.txt
bulb_channels-2.4.0.1.dist-info/RECORD
