Metadata-Version: 2.1
Name: bulb-channels
Version: 2.4.0.1
Summary: For of the django-channels project to make it compatible with bulb.
Home-page: http://github.com/Bulb-Core/bulb-channels
Author: LilianCruanes
Author-email: cruaneslilian@protonmail.com
License: BSD
Platform: UNKNOWN
Classifier: Development Status :: 5 - Production/Stable
Classifier: Environment :: Web Environment
Classifier: Framework :: Django
Classifier: Intended Audience :: Developers
Classifier: License :: OSI Approved :: BSD License
Classifier: Operating System :: OS Independent
Classifier: Programming Language :: Python
Classifier: Programming Language :: Python :: 3
Classifier: Programming Language :: Python :: 3.5
Classifier: Programming Language :: Python :: 3.6
Classifier: Programming Language :: Python :: 3.7
Classifier: Programming Language :: Python :: 3.8
Classifier: Topic :: Internet :: WWW/HTTP
Requires-Python: >=3.5
Requires-Dist: Django (>=2.2)
Requires-Dist: asgiref (~=3.2)
Requires-Dist: daphne (~=2.3)
Provides-Extra: tests
Requires-Dist: async-timeout (~=3.0) ; extra == 'tests'
Requires-Dist: async-generator (~=1.10) ; extra == 'tests'
Requires-Dist: coverage (~=4.5) ; extra == 'tests'
Requires-Dist: pytest-asyncio (~=0.10) ; extra == 'tests'
Requires-Dist: pytest-django (~=3.4) ; extra == 'tests'
Requires-Dist: pytest (~=4.4) ; extra == 'tests'
